taiwan_law_mcp/__init__.py
taiwan_law_mcp/__main__.py
taiwan_law_mcp/law_client.py
taiwan_law_mcp/server.py
taiwan_law_mcp-0.2.1.dist-info/METADATA
taiwan_law_mcp-0.2.1.dist-info/WHEEL
taiwan_law_mcp-0.2.1.dist-info/entry_points.txt
taiwan_law_mcp-0.2.1.dist-info/RECORD
