Metadata-Version: 2.4
Name: taiwan-law-mcp
Version: 0.2.1
Summary: 台灣法規查詢 MCP 伺服器 - 優化版本
Project-URL: Homepage, https://github.com/your-username/taiwan-law-mcp
Project-URL: Repository, https://github.com/your-username/taiwan-law-mcp
Project-URL: Issues, https://github.com/your-username/taiwan-law-mcp/issues
Author: Law MCP Developer
License-Expression: MIT
Classifier: Development Status :: 4 - Beta
Classifier: Intended Audience :: Developers
Classifier: License :: OSI Approved :: MIT License
Classifier: Programming Language :: Python :: 3
Classifier: Programming Language :: Python :: 3.8
Classifier: Programming Language :: Python :: 3.9
Classifier: Programming Language :: Python :: 3.10
Classifier: Programming Language :: Python :: 3.11
Classifier: Programming Language :: Python :: 3.12
Requires-Python: >=3.8
Requires-Dist: beautifulsoup4>=4.11.0
Requires-Dist: lxml>=4.9.0; sys_platform != 'win32'
Requires-Dist: mcp>=1.0.0
Requires-Dist: requests>=2.28.0
Provides-Extra: dev
Requires-Dist: black>=23.0.0; extra == 'dev'
Requires-Dist: pytest-asyncio>=0.21.0; extra == 'dev'
Requires-Dist: pytest>=7.0.0; extra == 'dev'
Requires-Dist: ruff>=0.1.0; extra == 'dev'
